PATK/__init__.py
patk-1.0.2.dist-info/METADATA
patk-1.0.2.dist-info/WHEEL
patk-1.0.2.dist-info/top_level.txt
patk-1.0.2.dist-info/RECORD
