Metadata-Version: 2.2
Name: PATK
Version: 1.0.2
Summary: A Tkinter-based rewrapping component library.
Home-page: https://github.com/Ashisheng2005/PATK
Author: HUZHAOJUN
Author-email: 3237495209@qq.com
Project-URL: Bug Reports, https://github.com/Ashisheng2005/PATK/issues
Project-URL: Source, https://github.com/Ashisheng2005/PATK
Keywords: tkinter,widget,PATK,TK
Classifier: Development Status :: 3 - Alpha
Classifier: Intended Audience :: Developers
Classifier: Topic :: Software Development :: Build Tools
Classifier: License :: OSI Approved :: MIT License
Classifier: Programming Language :: Python :: 3
Classifier: Programming Language :: Python :: 3.7
Classifier: Programming Language :: Python :: 3.8
Classifier: Programming Language :: Python :: 3.9
Classifier: Programming Language :: Python :: 3.10
Classifier: Programming Language :: Python :: 3 :: Only
Requires-Python: >=3.7, <4
Dynamic: author
Dynamic: author-email
Dynamic: classifier
Dynamic: description
Dynamic: description-content-type
Dynamic: home-page
Dynamic: keywords
Dynamic: project-url
Dynamic: requires-python
Dynamic: summary
